openapi_ts_client/__init__.py
openapi_ts_client/cli.py
openapi_ts_client/enums.py
openapi_ts_client/exceptions.py
openapi_ts_client/generator.py
openapi_ts_client/logging_config.py
openapi_ts_client/generators/__init__.py
openapi_ts_client/generators/angular/__init__.py
openapi_ts_client/generators/angular/anyof_extractor.py
openapi_ts_client/generators/angular/generator.py
openapi_ts_client/generators/angular/infrastructure.py
openapi_ts_client/generators/angular/models.py
openapi_ts_client/generators/angular/services.py
openapi_ts_client/generators/angular/type_mapper.py
openapi_ts_client/generators/axios/__init__.py
openapi_ts_client/generators/axios/api.py
openapi_ts_client/generators/axios/base.py
openapi_ts_client/generators/axios/common.py
openapi_ts_client/generators/axios/configuration.py
openapi_ts_client/generators/axios/docs.py
openapi_ts_client/generators/axios/generator.py
openapi_ts_client/generators/fetch/__init__.py
openapi_ts_client/generators/fetch/apis.py
openapi_ts_client/generators/fetch/docs.py
openapi_ts_client/generators/fetch/generator.py
openapi_ts_client/generators/fetch/models.py
openapi_ts_client/generators/fetch/runtime.py
openapi_ts_client/generators/shared/__init__.py
openapi_ts_client/generators/shared/anyof_extractor.py
openapi_ts_client/generators/shared/type_mapper.py
openapi_ts_client/templates/__init__.py
openapi_ts_client/templates/angular/README.md.j2
openapi_ts_client/templates/angular/api.base.service.ts.j2
openapi_ts_client/templates/angular/api.module.ts.j2
openapi_ts_client/templates/angular/api.ts.j2
openapi_ts_client/templates/angular/configuration.ts.j2
openapi_ts_client/templates/angular/encoder.ts.j2
openapi_ts_client/templates/angular/enum.ts.j2
openapi_ts_client/templates/angular/extracted_type.ts.j2
openapi_ts_client/templates/angular/index.ts.j2
openapi_ts_client/templates/angular/model.ts.j2
openapi_ts_client/templates/angular/models.ts.j2
openapi_ts_client/templates/angular/param.ts.j2
openapi_ts_client-1.4.0.dist-info/licenses/LICENSE
openapi_ts_client-1.4.0.dist-info/METADATA
openapi_ts_client-1.4.0.dist-info/WHEEL
openapi_ts_client-1.4.0.dist-info/entry_points.txt
openapi_ts_client-1.4.0.dist-info/top_level.txt
openapi_ts_client-1.4.0.dist-info/RECORD
