Metadata-Version: 2.4
Name: openapi-ts-client
Version: 1.4.0
Summary: Generate TypeScript clients from OpenAPI specifications
License: MIT License
Project-URL: Homepage, https://github.com/fa-krug/openapi-ts-client
Project-URL: Repository, https://github.com/fa-krug/openapi-ts-client
Keywords: openapi,swagger,typescript,client,generator,codegen
Classifier: Development Status :: 3 - Alpha
Classifier: Intended Audience :: Developers
Classifier: License :: OSI Approved :: MIT License
Classifier: Operating System :: OS Independent
Classifier: Programming Language :: Python :: 3
Classifier: Programming Language :: Python :: 3.8
Classifier: Programming Language :: Python :: 3.9
Classifier: Programming Language :: Python :: 3.10
Classifier: Programming Language :: Python :: 3.11
Classifier: Programming Language :: Python :: 3.12
Classifier: Topic :: Software Development :: Code Generators
Classifier: Typing :: Typed
Requires-Python: >=3.8
License-File: LICENSE
Requires-Dist: jinja2>=3.1.0
Requires-Dist: openapi-core>=0.19.0
Requires-Dist: pyyaml>=6.0
Provides-Extra: dev
Requires-Dist: ruff>=0.4.0; extra == "dev"
Requires-Dist: pre-commit>=3.0.0; extra == "dev"
Requires-Dist: pytest>=7.0; extra == "dev"
Requires-Dist: pytest-mock>=3.10; extra == "dev"
Requires-Dist: tree-sitter>=0.21; extra == "dev"
Requires-Dist: tree-sitter-typescript>=0.21; extra == "dev"
Dynamic: license-file
